[
  {
    "py/object": "model.contact.Contact",
    "firstname": "",
    "middlename": null,
    "lastname": "",
    "nickname": null,
    "file": "",
    "title": null,
    "company": null,
    "address": "",
    "homephone": null,
    "mobilephone": null,
    "workphone": null,
    "fax": null,
    "email": null,
    "email2": null,
    "email3": null,
    "homepage": null,
    "bday": "-",
    "bmonth": "-",
    "byear": null,
    "aday": "-",
    "amonth": "-",
    "ayear": null,
    "address2": null,
    "secondaryphone": null,
    "notes": null,
    "id": null,
    "all_phones_from_homepage": null,
    "all_emails_homepage": null
  },
  {
    "py/object": "model.contact.Contact",
    "firstname": "firstnameAc4 5 bRa",
    "middlename": null,
    "lastname": "lastnamevBrUvL",
    "nickname": null,
    "file": "",
    "title": null,
    "company": null,
    "address": "addressCW",
    "homephone": null,
    "mobilephone": null,
    "workphone": null,
    "fax": null,
    "email": null,
    "email2": null,
    "email3": null,
    "homepage": null,
    "bday": "-",
    "bmonth": "-",
    "byear": null,
    "aday": "-",
    "amonth": "-",
    "ayear": null,
    "address2": null,
    "secondaryphone": null,
    "notes": null,
    "id": null,
    "all_phones_from_homepage": null,
    "all_emails_homepage": null
  },
  {
    "py/object": "model.contact.Contact",
    "firstname": "firstnamezIna",
    "middlename": null,
    "lastname": "lastnamet Nb3sC",
    "nickname": null,
    "file": "",
    "title": null,
    "company": null,
    "address": "addressweI 1 Ptrbz 809",
    "homephone": null,
    "mobilephone": null,
    "workphone": null,
    "fax": null,
    "email": null,
    "email2": null,
    "email3": null,
    "homepage": null,
    "bday": "-",
    "bmonth": "-",
    "byear": null,
    "aday": "-",
    "amonth": "-",
    "ayear": null,
    "address2": null,
    "secondaryphone": null,
    "notes": null,
    "id": null,
    "all_phones_from_homepage": null,
    "all_emails_homepage": null
  },
  {
    "py/object": "model.contact.Contact",
    "firstname": "firstnameizXW jp",
    "middlename": null,
    "lastname": "lastname9FCH   ZQf D",
    "nickname": null,
    "file": "",
    "title": null,
    "company": null,
    "address": "address67k  tUoCjWoXc",
    "homephone": null,
    "mobilephone": null,
    "workphone": null,
    "fax": null,
    "email": null,
    "email2": null,
    "email3": null,
    "homepage": null,
    "bday": "-",
    "bmonth": "-",
    "byear": null,
    "aday": "-",
    "amonth": "-",
    "ayear": null,
    "address2": null,
    "secondaryphone": null,
    "notes": null,
    "id": null,
    "all_phones_from_homepage": null,
    "all_emails_homepage": null
  },
  {
    "py/object": "model.contact.Contact",
    "firstname": "firstname T",
    "middlename": null,
    "lastname": "lastnameXWVEe",
    "nickname": null,
    "file": "",
    "title": null,
    "company": null,
    "address": "addressc",
    "homephone": null,
    "mobilephone": null,
    "workphone": null,
    "fax": null,
    "email": null,
    "email2": null,
    "email3": null,
    "homepage": null,
    "bday": "-",
    "bmonth": "-",
    "byear": null,
    "aday": "-",
    "amonth": "-",
    "ayear": null,
    "address2": null,
    "secondaryphone": null,
    "notes": null,
    "id": null,
    "all_phones_from_homepage": null,
    "all_emails_homepage": null
  },
  {
    "py/object": "model.contact.Contact",
    "firstname": "firstnamec ",
    "middlename": null,
    "lastname": "lastnameho  Y",
    "nickname": null,
    "file": "",
    "title": null,
    "company": null,
    "address": "addressH S5xY6l8ptaTx",
    "homephone": null,
    "mobilephone": null,
    "workphone": null,
    "fax": null,
    "email": null,
    "email2": null,
    "email3": null,
    "homepage": null,
    "bday": "-",
    "bmonth": "-",
    "byear": null,
    "aday": "-",
    "amonth": "-",
    "ayear": null,
    "address2": null,
    "secondaryphone": null,
    "notes": null,
    "id": null,
    "all_phones_from_homepage": null,
    "all_emails_homepage": null
  }
]